README.rst
setup.py
knapsack01/__init__.py
knapsack01/knapsack.py
knapsack01.egg-info/PKG-INFO
knapsack01.egg-info/SOURCES.txt
knapsack01.egg-info/dependency_links.txt
knapsack01.egg-info/not-zip-safe
knapsack01.egg-info/top_level.txt
tests/__init__.py
tests/test_knapsack.py