Metadata-Version: 1.1
Name: knapsack01
Version: 0.0.1
Summary: Solving 0/1 Knapsack Problem
Home-page: https://github.com/pkuong/knapsack01
Author: Paulo Kuong
Author-email: paulo.kuong@gmail.com
License: MIT
Keywords: algorithm knapsack
Platform: UNKNOWN
Classifier: Development Status :: 3 - Alpha
Classifier: License :: OSI Approved :: MIT License
Classifier: Programming Language :: Python :: 3.4
